boilersaas/__init__.py
boilersaas/forms.py
boilersaas/models.py
boilersaas/routes.py
boilersaas/signin_social.py
boilersaas/types.py
boilersaas/templates/base.html
boilersaas/templates/blank.html
boilersaas/templates/dashboard.html
boilersaas/templates/for_tailwind.html
boilersaas/templates/index.html
boilersaas/templates/invite_create.html
boilersaas/templates/invites.html
boilersaas/templates/login.html
boilersaas/templates/logo.html
boilersaas/templates/register.html
boilersaas/templates/register_invite.html
boilersaas/templates/reset_request.html
boilersaas/templates/reset_request_with_token.html
boilersaas/templates/components/button_signin_facebook.html
boilersaas/templates/components/button_signin_google.html
boilersaas/templates/components/button_signin_x.html
boilersaas/templates/components/section_social_signin.html
boilersaas/templates/email/invite_send.html
boilersaas/templates/email/reset_password.html
boilersaas/templates/email/welcome.html
boilersaas/translations/PyBabel.cfg
boilersaas/translations/README.md
boilersaas/translations/es/LC_MESSAGES/messages.po
boilersaas/utils/__init__.py
boilersaas/utils/db.py
boilersaas/utils/locale.py
boilersaas/utils/mail.py
boilersaas-0.7.1.dist-info/METADATA
boilersaas-0.7.1.dist-info/WHEEL
boilersaas-0.7.1.dist-info/top_level.txt
boilersaas-0.7.1.dist-info/RECORD
