Metadata-Version: 2.2
Name: boilersaas
Version: 0.7.1
Summary: A boilerplate for flask SAAS apps, with social sign in, email confirmation, and more.
Home-page: http://example.com/your_package
Author: DS
Author-email: hello@davidstern.me
Keywords: flask,boilerplate,saas,app
Requires-Dist: Babel>=2.14.0
Requires-Dist: Flask>=3.0.2
Requires-Dist: flask-babel>=4.0.0
Requires-Dist: Flask-Dance>=7.1.0
Requires-Dist: Flask-Login>=0.6.3
Requires-Dist: Flask-Mail>=0.9.1
Requires-Dist: Flask-SQLAlchemy>=3.1.1
Requires-Dist: Flask-WTF>=1.2.1
Requires-Dist: itsdangerous>=2.1.2
Requires-Dist: python-dotenv>=1.0.1
Requires-Dist: requests>=2.31.0
Requires-Dist: SQLAlchemy>=2.0.28
Requires-Dist: Werkzeug>=3.0.1
Requires-Dist: WTForms>=3.1.2
Requires-Dist: email_validator>=2.1.1
Dynamic: author
Dynamic: author-email
Dynamic: home-page
Dynamic: keywords
Dynamic: requires-dist
Dynamic: summary
